Metadata-Version: 2.4
Name: lindera-python-cjk
Version: 2.1.1
Classifier: Programming Language :: Python :: 3
Classifier: Programming Language :: Python :: 3.10
Classifier: Programming Language :: Python :: 3.11
Classifier: Programming Language :: Python :: 3.12
Classifier: Programming Language :: Python :: 3.13
Classifier: Programming Language :: Python :: 3.14
Classifier: Programming Language :: Python :: 3.15
Classifier: License :: OSI Approved :: MIT License
Classifier: Operating System :: OS Independent
License-File: LICENSE
Summary: Python binding for Lindera with CJK dictionaries (IPADIC, ko-dic, CC-CEDICT)
Keywords: morphological,analysis,library,python
Home-Page: https://github.com/lindera/lindera
Author-email: Minoru Osuka <minoru.osuka@gmail.com>
License: MIT
Requires-Python: >=3.10, <3.15
